{
  "version": "1.1.1",
  "windows": {
    "main": {
      "main": true,
      "url": "app://editor/index.html",
      "windowType": "dockable",
      "x": 1713,
      "y": 0,
      "width": 1734,
      "height": 1399,
      "layout": {
        "type": "dock-h",
        "children": [
          {
            "width": 269,
            "height": 1281,
            "type": "dock-v",
            "children": [
              {
                "width": 269,
                "height": 593,
                "type": "panel",
                "active": 0,
                "children": [
                  "hierarchy"
                ]
              },
              {
                "width": 269,
                "height": 685,
                "type": "panel",
                "active": 0,
                "children": [
                  "assets"
                ]
              }
            ]
          },
          {
            "width": 1029,
            "height": 1281,
            "type": "dock-v",
            "children": [
              {
                "width": 1029,
                "height": 1011,
                "type": "dock-h",
                "children": [
                  {
                    "width": 464,
                    "height": 1011,
                    "type": "panel",
                    "active": 0,
                    "children": [
                      "scene"
                    ]
                  },
                  {
                    "width": 562,
                    "height": 1011,
                    "type": "panel",
                    "active": 0,
                    "children": [
                      "game-window"
                    ]
                  }
                ]
              },
              {
                "width": 1029,
                "height": 267,
                "type": "panel",
                "active": 0,
                "children": [
                  "console",
                  "timeline"
                ]
              }
            ]
          },
          {
            "width": 414,
            "height": 1281,
            "type": "panel",
            "active": 0,
            "children": [
              "inspector",
              "cocos-services"
            ]
          }
        ]
      },
      "panels": [
        "hierarchy",
        "assets",
        "scene",
        "game-window",
        "console",
        "timeline",
        "inspector",
        "cocos-services"
      ]
    },
    "window-1731766514354": {
      "main": false,
      "url": "unpack://static/window.html",
      "windowType": "dockable",
      "x": 1176,
      "y": 670,
      "width": 767,
      "height": 659,
      "layout": {
        "type": "dock-v",
        "children": []
      },
      "panels": []
    }
  },
  "panels": {
    "preferences": {
      "x": 1432,
      "y": 416,
      "width": 600,
      "height": 565
    },
    "simulator-debugger": {
      "x": 1176,
      "y": 670,
      "width": 767,
      "height": 659
    },
    "game-window": {
      "x": 2172,
      "y": 786,
      "width": 516,
      "height": 539
    },
    "project-settings": {
      "x": 1432,
      "y": 416,
      "width": 600,
      "height": 565
    }
  },
  "panelLabelWidth": {}
}
